PyUtils2024/01.抖音视频下载.py
PyUtils2024/DownloadBilibili.py
PyUtils2024/__init__.py
PyUtils2024/utils.py
pyutils2024-0.0.10.dist-info/licenses/LICENSE
pyutils2024-0.0.10.dist-info/METADATA
pyutils2024-0.0.10.dist-info/WHEEL
pyutils2024-0.0.10.dist-info/top_level.txt
pyutils2024-0.0.10.dist-info/RECORD
