Metadata-Version: 2.4
Name: PyUtils2024
Version: 0.0.10
Summary: tools
Author-email: Lixin <lixin1226@163.com>
Classifier: Programming Language :: Python :: 3
Classifier: License :: OSI Approved :: MIT License
Classifier: Operating System :: OS Independent
Requires-Python: >=3.8
License-File: LICENSE
Dynamic: license-file
